pagr/__init__.py
pagr/mbook.py
pagr/runner.py
pagr/services/__init__.py
pagr/services/bitbucket.py
pagr/services/influxdb.py
pagr/services/jenkins.py
pagr/services/jira.py
pagr-0.0.3.dist-info/LICENSE
pagr-0.0.3.dist-info/METADATA
pagr-0.0.3.dist-info/WHEEL
pagr-0.0.3.dist-info/top_level.txt
pagr-0.0.3.dist-info/RECORD
