Metadata-Version: 2.1
Name: pagr
Version: 0.0.3
Summary: A Python Aggregator
Home-page: https://github.com/defreng/python-pagr
Author: Alexander Hungenberg
Author-email: alexander.hungenberg@gmail.com
License: UNKNOWN
Platform: UNKNOWN
Classifier: Programming Language :: Python :: 3
Classifier: License :: OSI Approved :: MIT License
Classifier: Operating System :: OS Independent
Requires-Dist: pyyaml
